django_hawkeye/__init__.py
django_hawkeye/apps.py
django_hawkeye/checks.py
django_hawkeye/expressions.py
django_hawkeye/indexes.py
django_hawkeye/mixins.py
django_hawkeye/operations.py
django_hawkeye/search.py
django_hawkeye/migrations/__init__.py
django_hawkeye-0.4.0.dist-info/METADATA
django_hawkeye-0.4.0.dist-info/WHEEL
django_hawkeye-0.4.0.dist-info/RECORD
