Metadata-Version: 2.4
Name: django-hawkeye
Version: 0.4.0
Summary: Django-hawkeye full-text search using PostgreSQL pg_textsearch - a lightweight Elasticsearch alternative
Project-URL: Homepage, https://github.com/FarhanAliRaza/django-hawkeye
Project-URL: Documentation, https://github.com/FarhanAliRaza/django-hawkeye#readme
Project-URL: Repository, https://github.com/FarhanAliRaza/django-hawkeye
Author-email: Farhan Ali Raza <farhanaliraza@gmail.com>
License: MIT
Keywords: bm25,django,elasticsearch-alternative,full-text-search,postgresql,search
Classifier: Development Status :: 3 - Alpha
Classifier: Framework :: Django
Classifier: Framework :: Django :: 4.2
Classifier: Framework :: Django :: 5.2
Classifier: Framework :: Django :: 6.0
Classifier: Intended Audience :: Developers
Classifier: License :: OSI Approved :: MIT License
Classifier: Operating System :: OS Independent
Classifier: Programming Language :: Python :: 3
Classifier: Programming Language :: Python :: 3.10
Classifier: Programming Language :: Python :: 3.11
Classifier: Programming Language :: Python :: 3.12
Classifier: Topic :: Database
Classifier: Topic :: Text Processing :: Indexing
Requires-Python: >=3.10
Requires-Dist: django!=5.0.*,!=5.1.*,>=4.2
Requires-Dist: django-cmd>=2.7
Requires-Dist: psycopg>=3.0
